genie/trafficgen/__init__.py
genie/trafficgen/trafficgen.py
genie/trafficgen/ios/__init__.py
genie/trafficgen/ios/pagent/__init__.py
genie/trafficgen/ios/pagent/implementation.py
genie/trafficgen/ios/pagent/pagentflow.py
genie/trafficgen/ios/pagent/utils.py
genie/trafficgen/ios/pagent/templates/dhcpv4.ptd
genie/trafficgen/ios/pagent/templates/dhcpv6.ptd
genie/trafficgen/ixianative/__init__.py
genie/trafficgen/ixianative/implementation.py
genie/trafficgen/ixiangpf/__init__.py
genie/trafficgen/ixiangpf/implementation.py
genie/trafficgen/ixiarestpy/__init__.py
genie/trafficgen/ixiarestpy/implementation.py
genie/trafficgen/pagent/__init__.py
genie/trafficgen/pagent/implementation.py
genie/trafficgen/pagent/pagentflow.py
genie/trafficgen/pagent/utils.py
genie/trafficgen/spirent/__init__.py
genie/trafficgen/spirent/implementation.py
genie/trafficgen/tests/test_abstract.py
genie/trafficgen/tests/test_ixianative.py
genie/trafficgen/tests/test_ixiangpf.py
genie/trafficgen/tests/test_ixiarestpy.py
genie/trafficgen/tests/test_pagent.py
genie/trafficgen/tests/test_trex.py
genie/trafficgen/trex/__init__.py
genie/trafficgen/trex/implementation.py
genie.trafficgen-25.9.dist-info/METADATA
genie.trafficgen-25.9.dist-info/WHEEL
genie.trafficgen-25.9.dist-info/entry_points.txt
genie.trafficgen-25.9.dist-info/top_level.txt
genie.trafficgen-25.9.dist-info/RECORD
