Metadata-Version: 2.1
Name: genie.trafficgen
Version: 25.9
Summary: Genie Library for traffic generator connection support
Home-page: https://developer.cisco.com/pyats
Author: Cisco Systems Inc.
Author-email: pyats-support-ext@cisco.com
License: Apache 2.0
Keywords: genie traffic pyats cisco
Classifier: Development Status :: 6 - Mature
Classifier: Development Status :: 5 - Production/Stable
Classifier: Environment :: Console
Classifier: Intended Audience :: Developers
Classifier: Intended Audience :: Telecommunications Industry
Classifier: Intended Audience :: Information Technology
Classifier: Intended Audience :: System Administrators
Classifier: License :: OSI Approved :: Apache Software License
Classifier: Operating System :: MacOS
Classifier: Operating System :: POSIX :: Linux
Classifier: Programming Language :: Python :: 3.13
Classifier: Programming Language :: Python :: 3.12
Classifier: Programming Language :: Python :: 3.11
Classifier: Programming Language :: Python :: 3.10
Classifier: Programming Language :: Python :: 3.9
Classifier: Programming Language :: Python :: 3 :: Only
Classifier: Programming Language :: Python :: Implementation :: CPython
Classifier: Topic :: Software Development :: Testing
Classifier: Topic :: Software Development :: Build Tools
Classifier: Topic :: Software Development :: Libraries
Classifier: Topic :: Software Development :: Libraries :: Python Modules
Requires-Dist: genie
Requires-Dist: unicon
Requires-Dist: prettytable
Requires-Dist: IxNetwork
Requires-Dist: ixnetwork-restpy
Requires-Dist: setuptools
Requires-Dist: wheel
Requires-Dist: stcrestclient
Provides-Extra: dev
Requires-Dist: coverage; extra == "dev"
Requires-Dist: restview; extra == "dev"
Requires-Dist: Sphinx; extra == "dev"
Requires-Dist: sphinx-rtd-theme; extra == "dev"
Requires-Dist: sphinxcontrib-mockautodoc; extra == "dev"
Requires-Dist: stcrestclient; extra == "dev"
